{"legislative_session": "2025", "identifier": "HB16", "title": "LIABILITY/CIVIL: Provides relative to the limitation of civil liability for nonprofits that donate medical supplies", "from_organization": "~{\"classification\": \"lower\"}", "classification": ["bill"], "subject": [], "abstracts": [], "other_titles": [], "other_identifiers": [], "actions": [{"description": "Effective date: 08/01/2025.", "date": "2025-06-11", "organization_id": "~{\"classification\": \"lower\"}", "classification": [], "related_entities": []}, {"description": "Signed by the Governor. Becomes Act No. 234.", "date": "2025-06-11", "organization_id": "~{\"classification\": \"lower\"}", "classification": ["became-law", "executive-signature"], "related_entities": []}, {"description": "Sent to the Governor for executive approval.", "date": "2025-06-09", "organization_id": "~{\"classification\": \"lower\"}", "classification": ["executive-receipt"], "related_entities": []}, {"description": "Signed by the President of the Senate.", "date": "2025-06-08", "organization_id": "~{\"classification\": \"upper\"}", "classification": [], "related_entities": []}, {"description": "Enrolled and signed by the Speaker of the House.", "date": "2025-06-08", "organization_id": "~{\"classification\": \"lower\"}", "classification": ["enrolled"], "related_entities": []}, {"description": "Read by title, roll called, yeas 87, nays 0, Senate amendments concurred in.", "date": "2025-06-04", "organization_id": "~{\"classification\": \"lower\"}", "classification": [], "related_entities": []}, {"description": "Scheduled for concurrence on 06/04/2025.", "date": "2025-06-03", "organization_id": "~{\"classification\": \"lower\"}", "classification": [], "related_entities": []}, {"description": "Received from the Senate with amendments.", "date": "2025-06-02", "organization_id": "~{\"classification\": \"lower\"}", "classification": ["receipt"], "related_entities": []}, {"description": "The amended bill was read by title, passed by a vote of 39 yeas and 0 nays, and ordered returned to the House.  Motion to reconsider tabled.", "date": "2025-06-02", "organization_id": "~{\"classification\": \"upper\"}", "classification": ["passage"], "related_entities": []}, {"description": "Reported without Legislative Bureau amendments.  Read by title and passed to third reading and final passage.", "date": "2025-06-01", "organization_id": "~{\"classification\": \"upper\"}", "classification": ["reading-3"], "related_entities": []}, {"description": "Committee amendments read and adopted.  Read by title and referred to the Legislative Bureau.", "date": "2025-06-01", "organization_id": "~{\"classification\": \"upper\"}", "classification": [], "related_entities": []}, {"description": "Reported with amendments.", "date": "2025-05-29", "organization_id": "~{\"classification\": \"upper\"}", "classification": ["committee-passage-favorable"], "related_entities": []}, {"description": "Read second time by title and referred to the Committee on Judiciary A.", "date": "2025-05-07", "organization_id": "~{\"classification\": \"upper\"}", "classification": ["reading-2", "referral-committee"], "related_entities": []}, {"description": "Received in the Senate.  Rules suspended.  Read first time by title and placed on the Calendar for a second reading.", "date": "2025-05-06", "organization_id": "~{\"classification\": \"upper\"}", "classification": ["reading-1"], "related_entities": []}, {"description": "Read third time by title, roll called on final passage, yeas 98, nays 0. Finally passed, title adopted, ordered to the Senate.", "date": "2025-05-06", "organization_id": "~{\"classification\": \"lower\"}", "classification": ["passage"], "related_entities": []}, {"description": "Scheduled for floor debate on 05/06/2025.", "date": "2025-05-05", "organization_id": "~{\"classification\": \"lower\"}", "classification": [], "related_entities": []}, {"description": "Read by title, ordered engrossed, passed to 3rd reading.", "date": "2025-04-29", "organization_id": "~{\"classification\": \"lower\"}", "classification": ["reading-3"], "related_entities": []}, {"description": "Reported favorably (9-0).", "date": "2025-04-28", "organization_id": "~{\"classification\": \"lower\"}", "classification": ["committee-passage-favorable"], "related_entities": []}, {"description": "Read by title, under the rules, referred to the Committee on Civil Law and Procedure.", "date": "2025-04-14", "organization_id": "~{\"classification\": \"lower\"}", "classification": ["referral-committee"], "related_entities": []}, {"description": "First appeared in the Interim Calendar on 2/28/2025.", "date": "2025-02-28", "organization_id": "~{\"classification\": \"lower\"}", "classification": [], "related_entities": []}, {"description": "Under the rules, provisionally referred to the Committee on Civil Law and Procedure.", "date": "2025-02-25", "organization_id": "~{\"classification\": \"lower\"}", "classification": ["referral-committee"], "related_entities": []}, {"description": "Prefiled.", "date": "2025-02-25", "organization_id": "~{\"classification\": \"lower\"}", "classification": ["filing"], "related_entities": []}], "sponsorships": [{"name": "Laurie Schlegel", "classification": "primary", "entity_type": "person", "primary": true, "person_id": "~{\"name\": \"Laurie Schlegel\"}", "organization_id": null}, {"name": "Beryl Amedee", "classification": "cosponsor", "entity_type": "person", "primary": false, "person_id": "~{\"name\": \"Beryl Amedee\"}", "organization_id": null}, {"name": "Stephanie Berault", "classification": "cosponsor", "entity_type": "person", "primary": false, "person_id": "~{\"name\": \"Stephanie Berault\"}", "organization_id": null}, {"name": "Rhonda Butler", "classification": "cosponsor", "entity_type": "person", "primary": false, "person_id": "~{\"name\": \"Rhonda Butler\"}", "organization_id": null}, {"name": "Kim Carver", "classification": "cosponsor", "entity_type": "person", "primary": false, "person_id": "~{\"name\": \"Kim Carver\"}", "organization_id": null}, {"name": "Paula Davis", "classification": "cosponsor", "entity_type": "person", "primary": false, "person_id": "~{\"name\": \"Paula Davis\"}", "organization_id": null}, {"name": "Phillip DeVillier", "classification": "cosponsor", "entity_type": "person", "primary": false, "person_id": "~{\"name\": \"Phillip DeVillier\"}", "organization_id": null}, {"name": "Julie Emerson", "classification": "cosponsor", "entity_type": "person", "primary": false, "person_id": "~{\"name\": \"Julie Emerson\"}", "organization_id": null}, {"name": "Barbara Reich Freiberg", "classification": "cosponsor", "entity_type": "person", "primary": false, "person_id": "~{\"name\": \"Barbara Reich Freiberg\"}", "organization_id": null}, {"name": "Dodie Horton", "classification": "cosponsor", "entity_type": "person", "primary": false, "person_id": "~{\"name\": \"Dodie Horton\"}", "organization_id": null}, {"name": "Jack McFarland", "classification": "cosponsor", "entity_type": "person", "primary": false, "person_id": "~{\"name\": \"Jack McFarland\"}", "organization_id": null}, {"name": "Charles Owen", "classification": "cosponsor", "entity_type": "person", "primary": false, "person_id": "~{\"name\": \"Charles Owen\"}", "organization_id": null}, {"name": "Sylvia Taylor", "classification": "cosponsor", "entity_type": "person", "primary": false, "person_id": "~{\"name\": \"Sylvia Taylor\"}", "organization_id": null}, {"name": "Debbie Villio", "classification": "cosponsor", "entity_type": "person", "primary": false, "person_id": "~{\"name\": \"Debbie Villio\"}", "organization_id": null}, {"name": "John Wyble", "classification": "cosponsor", "entity_type": "person", "primary": false, "person_id": "~{\"name\": \"John Wyble\"}", "organization_id": null}], "related_bills": [], "versions": [{"note": "HB16 Act", "links": [{"url": "https://www.legis.la.gov/Legis/ViewDocument.aspx?d=1425490", "media_type": "application/pdf"}], "date": "", "classification": ""}, {"note": "HB16 Enrolled", "links": [{"url": "https://www.legis.la.gov/Legis/ViewDocument.aspx?d=1422138", "media_type": "application/pdf"}], "date": "", "classification": ""}, {"note": "HB16 Engrossed", "links": [{"url": "https://www.legis.la.gov/Legis/ViewDocument.aspx?d=1408875", "media_type": "application/pdf"}], "date": "", "classification": ""}, {"note": "HB16 Original", "links": [{"url": "https://www.legis.la.gov/Legis/ViewDocument.aspx?d=1394626", "media_type": "application/pdf"}], "date": "", "classification": ""}, {"note": "Senate Committee Amendment, #2322, JUDA, Adopted", "links": [{"url": "https://www.legis.la.gov/Legis/ViewDocument.aspx?d=1418617", "media_type": "application/pdf"}], "date": "", "classification": ""}, {"note": "Senate Committee Amendment, #2320, JUDA, Draft", "links": [{"url": "https://www.legis.la.gov/Legis/ViewDocument.aspx?d=1418612", "media_type": "application/pdf"}], "date": "", "classification": ""}], "documents": [{"note": "Resume Digest for HB16", "links": [{"url": "https://www.legis.la.gov/Legis/ViewDocument.aspx?d=1427883", "media_type": "application/pdf"}], "date": "", "classification": ""}, {"note": "Summary of Senate Amendments to HB16", "links": [{"url": "https://www.legis.la.gov/Legis/ViewDocument.aspx?d=1420954", "media_type": "application/pdf"}], "date": "", "classification": ""}, {"note": "Senate Green Sheet Digest for HB16", "links": [{"url": "https://www.legis.la.gov/Legis/ViewDocument.aspx?d=1419207", "media_type": "application/pdf"}], "date": "", "classification": ""}, {"note": "Digest of HB16 Engrossed", "links": [{"url": "https://www.legis.la.gov/Legis/ViewDocument.aspx?d=1409137", "media_type": "application/pdf"}], "date": "", "classification": ""}, {"note": "Digest of HB16 Original", "links": [{"url": "https://www.legis.la.gov/Legis/ViewDocument.aspx?d=1394629", "media_type": "application/pdf"}], "date": "", "classification": ""}], "citations": [], "sources": [{"url": "https://www.legis.la.gov/Legis/BillInfo.aspx?i=247899", "note": ""}], "extras": {}, "jurisdiction": {"id": "ocd-jurisdiction/country:us/state:la/government", "name": "Louisiana", "classification": "state", "division_id": "ocd-division/country:us/state:la"}, "scraped_at": "2025-07-28T18:52:32+00:00", "_id": "049ed1bc-6be4-11f0-99c6-2a6b771ef9eb"}