{"legislative_session": "2025", "identifier": "HR231", "title": "SPECIAL DAY/WEEK/MONTH: Commends the American Therapy Association-Louisiana Chapter for outstanding achievements and designates May 29, 2025, as Physical Therapy Day at the state capitol.", "from_organization": "~{\"classification\": \"lower\"}", "classification": ["resolution"], "subject": [], "abstracts": [], "other_titles": [], "other_identifiers": [], "actions": [{"description": "Taken by the Clerk of the House and presented to the Secretary of State in accordance with the Rules of the House.", "date": "2025-05-30", "organization_id": "~{\"classification\": \"lower\"}", "classification": [], "related_entities": []}, {"description": "Enrolled and signed by the Speaker of the House.", "date": "2025-05-29", "organization_id": "~{\"classification\": \"lower\"}", "classification": ["enrolled"], "related_entities": []}, {"description": "Read by title, rules suspended, adopted.", "date": "2025-05-28", "organization_id": "~{\"classification\": \"lower\"}", "classification": [], "related_entities": []}], "sponsorships": [{"name": "Joe Stagni", "classification": "primary", "entity_type": "person", "primary": true, "person_id": "~{\"name\": \"Joe Stagni\"}", "organization_id": null}], "related_bills": [], "versions": [{"note": "HR231 Enrolled", "links": [{"url": "https://www.legis.la.gov/Legis/ViewDocument.aspx?d=1419181", "media_type": "application/pdf"}], "date": "", "classification": ""}, {"note": "HR231 Original", "links": [{"url": "https://www.legis.la.gov/Legis/ViewDocument.aspx?d=1418646", "media_type": "application/pdf"}], "date": "", "classification": ""}], "documents": [{"note": "Digest of HR231 Original", "links": [{"url": "https://www.legis.la.gov/Legis/ViewDocument.aspx?d=1418647", "media_type": "application/pdf"}], "date": "", "classification": ""}], "citations": [], "sources": [{"url": "https://www.legis.la.gov/Legis/BillInfo.aspx?i=249344", "note": ""}], "extras": {}, "jurisdiction": {"id": "ocd-jurisdiction/country:us/state:la/government", "name": "Louisiana", "classification": "state", "division_id": "ocd-division/country:us/state:la"}, "scraped_at": "2025-07-28T18:53:08+00:00", "_id": "1a37df82-6be4-11f0-99c6-2a6b771ef9eb"}