{"legislative_session": "2025", "identifier": "HR375", "title": "COMMENDATIONS: Commends David Sickey on his election as chairman of the Coushatta Tribe of Louisiana", "from_organization": "~{\"classification\": \"lower\"}", "classification": ["resolution"], "subject": [], "abstracts": [], "other_titles": [], "other_identifiers": [], "actions": [{"description": "Taken by the Clerk of the House and presented to the Secretary of State in accordance with the Rules of the House.", "date": "2025-06-13", "organization_id": "~{\"classification\": \"lower\"}", "classification": [], "related_entities": []}, {"description": "Enrolled and signed by the Speaker of the House.", "date": "2025-06-12", "organization_id": "~{\"classification\": \"lower\"}", "classification": ["enrolled"], "related_entities": []}, {"description": "Read by title, rules suspended, adopted.", "date": "2025-06-12", "organization_id": "~{\"classification\": \"lower\"}", "classification": [], "related_entities": []}], "sponsorships": [{"name": "R. Dewith Carrier", "classification": "primary", "entity_type": "person", "primary": true, "person_id": "~{\"name\": \"R. Dewith Carrier\"}", "organization_id": null}], "related_bills": [], "versions": [{"note": "HR375 Enrolled", "links": [{"url": "https://www.legis.la.gov/Legis/ViewDocument.aspx?d=1424852", "media_type": "application/pdf"}], "date": "", "classification": ""}, {"note": "HR375 Original", "links": [{"url": "https://www.legis.la.gov/Legis/ViewDocument.aspx?d=1424847", "media_type": "application/pdf"}], "date": "", "classification": ""}], "documents": [{"note": "Resume Digest for HR375", "links": [{"url": "https://www.legis.la.gov/Legis/ViewDocument.aspx?d=1428917", "media_type": "application/pdf"}], "date": "", "classification": ""}, {"note": "Digest of HR375 Original", "links": [{"url": "https://www.legis.la.gov/Legis/ViewDocument.aspx?d=1424848", "media_type": "application/pdf"}], "date": "", "classification": ""}], "citations": [], "sources": [{"url": "https://www.legis.la.gov/Legis/BillInfo.aspx?i=249566", "note": ""}], "extras": {}, "jurisdiction": {"id": "ocd-jurisdiction/country:us/state:la/government", "name": "Louisiana", "classification": "state", "division_id": "ocd-division/country:us/state:la"}, "scraped_at": "2025-07-28T18:53:11+00:00", "_id": "1be5506c-6be4-11f0-99c6-2a6b771ef9eb"}