{"legislative_session": "2025", "identifier": "SR95", "title": "SPECIAL DAY/WEEK/MONTH: Recognizes May 9, 2025, as Child Care Provider Appreciation Day.", "from_organization": "~{\"classification\": \"upper\"}", "classification": ["resolution"], "subject": [], "abstracts": [], "other_titles": [], "other_identifiers": [], "actions": [{"description": "Enrolled.  Signed by the President of the Senate and sent to the Secretary of State by the Secretary of the Senate.", "date": "2025-05-14", "organization_id": "~{\"classification\": \"upper\"}", "classification": ["enrolled"], "related_entities": []}, {"description": "Introduced in the Senate; read by title.  Rules suspended.  Read second time by title and adopted.", "date": "2025-05-08", "organization_id": "~{\"classification\": \"upper\"}", "classification": ["reading-2"], "related_entities": []}], "sponsorships": [{"name": "Beth Mizell", "classification": "primary", "entity_type": "person", "primary": true, "person_id": "~{\"name\": \"Beth Mizell\"}", "organization_id": null}], "related_bills": [], "versions": [{"note": "SR95 Enrolled", "links": [{"url": "https://www.legis.la.gov/Legis/ViewDocument.aspx?d=1413016", "media_type": "application/pdf"}], "date": "", "classification": ""}, {"note": "SR95 Original", "links": [{"url": "https://www.legis.la.gov/Legis/ViewDocument.aspx?d=1412855", "media_type": "application/pdf"}], "date": "", "classification": ""}], "documents": [{"note": "Resume Digest for SR95", "links": [{"url": "https://www.legis.la.gov/Legis/ViewDocument.aspx?d=1428192", "media_type": "application/pdf"}], "date": "", "classification": ""}, {"note": "Digest of SR95 Original", "links": [{"url": "https://www.legis.la.gov/Legis/ViewDocument.aspx?d=1412857", "media_type": "application/pdf"}], "date": "", "classification": ""}], "citations": [], "sources": [{"url": "https://www.legis.la.gov/Legis/BillInfo.aspx?i=249122", "note": ""}], "extras": {}, "jurisdiction": {"id": "ocd-jurisdiction/country:us/state:la/government", "name": "Louisiana", "classification": "state", "division_id": "ocd-division/country:us/state:la"}, "scraped_at": "2025-07-28T17:58:39+00:00", "_id": "7de3c09e-6bdc-11f0-add2-9240627cf73f"}