{
  "legislative_session": "2025",
  "identifier": "HB481",
  "title": "ALCOHOLIC BEVERAGE PERMT: Provides relative to limitations on the issuance of certain alcoholic beverage permits",
  "from_organization": "~{\"classification\": \"lower\"}",
  "classification": [
    "bill"
  ],
  "subject": [],
  "abstracts": [],
  "other_titles": [],
  "other_identifiers": [],
  "actions": [
    {
      "description": "Effective date: 08/01/2025.",
      "date": "2025-07-01",
      "organization_id": "~{\"classification\": \"lower\"}",
      "classification": [],
      "related_entities": []
    },
    {
      "description": "Becomes Act No. 503 without the Governor's signature.",
      "date": "2025-07-01",
      "organization_id": "~{\"classification\": \"lower\"}",
      "classification": [
        "became-law"
      ],
      "related_entities": []
    },
    {
      "description": "Sent to the Governor for executive approval.",
      "date": "2025-06-09",
      "organization_id": "~{\"classification\": \"lower\"}",
      "classification": [
        "executive-receipt"
      ],
      "related_entities": []
    },
    {
      "description": "Signed by the President of the Senate.",
      "date": "2025-06-09",
      "organization_id": "~{\"classification\": \"upper\"}",
      "classification": [],
      "related_entities": []
    },
    {
      "description": "Enrolled and signed by the Speaker of the House.",
      "date": "2025-06-09",
      "organization_id": "~{\"classification\": \"lower\"}",
      "classification": [
        "enrolled"
      ],
      "related_entities": []
    },
    {
      "description": "Received from the Senate without amendments.",
      "date": "2025-06-08",
      "organization_id": "~{\"classification\": \"lower\"}",
      "classification": [
        "receipt"
      ],
      "related_entities": []
    },
    {
      "description": "Rules suspended. Read by title, passed by a vote of 34 yeas and 5 nays, and ordered returned to the House.  Motion to reconsider tabled.",
      "date": "2025-06-08",
      "organization_id": "~{\"classification\": \"upper\"}",
      "classification": [
        "passage"
      ],
      "related_entities": []
    },
    {
      "description": "Reported without Legislative Bureau amendments.  Read by title and passed to third reading and final passage.",
      "date": "2025-06-04",
      "organization_id": "~{\"classification\": \"upper\"}",
      "classification": [
        "reading-3"
      ],
      "related_entities": []
    },
    {
      "description": "Reported favorably.  Rules suspended. Read by title and referred to the Legislative Bureau.",
      "date": "2025-06-03",
      "organization_id": "~{\"classification\": \"upper\"}",
      "classification": [
        "committee-passage-favorable"
      ],
      "related_entities": []
    },
    {
      "description": "Read second time by title and referred to the Committee on Judiciary B.",
      "date": "2025-05-27",
      "organization_id": "~{\"classification\": \"upper\"}",
      "classification": [
        "reading-2",
        "referral-committee"
      ],
      "related_entities": []
    },
    {
      "description": "Received in the Senate.  Rules suspended.  Read first time by title and placed on the Calendar for a second reading.",
      "date": "2025-05-21",
      "organization_id": "~{\"classification\": \"upper\"}",
      "classification": [
        "reading-1"
      ],
      "related_entities": []
    },
    {
      "description": "Read third time by title, amended, roll called on final passage, yeas 92, nays 0. Finally passed, title adopted, ordered to the Senate.",
      "date": "2025-05-20",
      "organization_id": "~{\"classification\": \"lower\"}",
      "classification": [
        "passage"
      ],
      "related_entities": []
    },
    {
      "description": "Scheduled for floor debate on 05/20/2025.",
      "date": "2025-05-19",
      "organization_id": "~{\"classification\": \"lower\"}",
      "classification": [],
      "related_entities": []
    },
    {
      "description": "Read by title, amended, ordered engrossed, passed to 3rd reading.",
      "date": "2025-05-19",
      "organization_id": "~{\"classification\": \"lower\"}",
      "classification": [
        "reading-3"
      ],
      "related_entities": []
    },
    {
      "description": "Reported with amendments (12-0).",
      "date": "2025-05-15",
      "organization_id": "~{\"classification\": \"lower\"}",
      "classification": [
        "committee-passage-favorable"
      ],
      "related_entities": []
    },
    {
      "description": "Read by title, under the rules, referred to the Committee on Judiciary.",
      "date": "2025-04-14",
      "organization_id": "~{\"classification\": \"lower\"}",
      "classification": [
        "referral-committee"
      ],
      "related_entities": []
    },
    {
      "description": "Under the rules, provisionally referred to the Committee on Judiciary.",
      "date": "2025-04-04",
      "organization_id": "~{\"classification\": \"lower\"}",
      "classification": [
        "referral-committee"
      ],
      "related_entities": []
    },
    {
      "description": "Prefiled.",
      "date": "2025-04-04",
      "organization_id": "~{\"classification\": \"lower\"}",
      "classification": [
        "filing"
      ],
      "related_entities": []
    }
  ],
  "sponsorships": [
    {
      "name": "Tammy Phelps",
      "classification": "primary",
      "entity_type": "person",
      "primary": true,
      "person_id": "~{\"name\": \"Tammy Phelps\"}",
      "organization_id": null
    }
  ],
  "related_bills": [],
  "versions": [
    {
      "note": "HB481 Act 503",
      "links": [
        {
          "url": "https://www.legis.la.gov/Legis/ViewDocument.aspx?d=1427695",
          "media_type": "application/pdf"
        }
      ],
      "date": "",
      "classification": ""
    },
    {
      "note": "HB481 Enrolled",
      "links": [
        {
          "url": "https://www.legis.la.gov/Legis/ViewDocument.aspx?d=1422952",
          "media_type": "application/pdf"
        }
      ],
      "date": "",
      "classification": ""
    },
    {
      "note": "HB481 Reengrossed",
      "links": [
        {
          "url": "https://www.legis.la.gov/Legis/ViewDocument.aspx?d=1416661",
          "media_type": "application/pdf"
        }
      ],
      "date": "",
      "classification": ""
    },
    {
      "note": "HB481 Engrossed",
      "links": [
        {
          "url": "https://www.legis.la.gov/Legis/ViewDocument.aspx?d=1415399",
          "media_type": "application/pdf"
        }
      ],
      "date": "",
      "classification": ""
    },
    {
      "note": "HB481 Original",
      "links": [
        {
          "url": "https://www.legis.la.gov/Legis/ViewDocument.aspx?d=1403993",
          "media_type": "application/pdf"
        }
      ],
      "date": "",
      "classification": ""
    },
    {
      "note": "House Floor Amendment, #3202, Phelps, Adopted",
      "links": [
        {
          "url": "https://www.legis.la.gov/Legis/ViewDocument.aspx?d=1416353",
          "media_type": "application/pdf"
        }
      ],
      "date": "",
      "classification": ""
    },
    {
      "note": "House Committee Amendment, #2981, JUD, Adopted",
      "links": [
        {
          "url": "https://www.legis.la.gov/Legis/ViewDocument.aspx?d=1415382",
          "media_type": "application/pdf"
        }
      ],
      "date": "",
      "classification": ""
    },
    {
      "note": "House Committee Amendment, #2611, JUD, Draft",
      "links": [
        {
          "url": "https://www.legis.la.gov/Legis/ViewDocument.aspx?d=1413422",
          "media_type": "application/pdf"
        }
      ],
      "date": "",
      "classification": ""
    }
  ],
  "documents": [
    {
      "note": "Resume Digest for HB481",
      "links": [
        {
          "url": "https://www.legis.la.gov/Legis/ViewDocument.aspx?d=1428020",
          "media_type": "application/pdf"
        }
      ],
      "date": "",
      "classification": ""
    },
    {
      "note": "Digest of HB481 Reengrossed",
      "links": [
        {
          "url": "https://www.legis.la.gov/Legis/ViewDocument.aspx?d=1416715",
          "media_type": "application/pdf"
        }
      ],
      "date": "",
      "classification": ""
    },
    {
      "note": "Digest of HB481 Engrossed",
      "links": [
        {
          "url": "https://www.legis.la.gov/Legis/ViewDocument.aspx?d=1415501",
          "media_type": "application/pdf"
        }
      ],
      "date": "",
      "classification": ""
    },
    {
      "note": "Digest of HB481 Original",
      "links": [
        {
          "url": "https://www.legis.la.gov/Legis/ViewDocument.aspx?d=1404017",
          "media_type": "application/pdf"
        }
      ],
      "date": "",
      "classification": ""
    }
  ],
  "citations": [],
  "sources": [
    {
      "url": "https://www.legis.la.gov/Legis/BillInfo.aspx?i=248513",
      "note": ""
    }
  ],
  "extras": {},
  "jurisdiction": {
    "id": "ocd-jurisdiction/country:us/state:la/government",
    "name": "Louisiana",
    "classification": "state",
    "division_id": "ocd-division/country:us/state:la"
  },
  "scraped_at": "2025-07-28T18:01:47+00:00",
  "_id": "edd0b628-6bdc-11f0-add2-9240627cf73f"
}